statmanager/__init__.py
statmanager/ancova_functions.py
statmanager/between_group_functions.py
statmanager/bootstrap_functions.py
statmanager/correlation_functions.py
statmanager/effectsize_functions.py
statmanager/figure_for_howtouse_eng.csv
statmanager/figure_for_howtouse_kor.csv
statmanager/frequency_functions.py
statmanager/homoskedasticity_functions.py
statmanager/logo.png
statmanager/making_figure.py
statmanager/manager.py
statmanager/menu_for_howtouse.py
statmanager/menu_for_howtouse_eng.csv
statmanager/menu_for_howtouse_kor.csv
statmanager/messages_for_reporting.py
statmanager/normality_functions.py
statmanager/posthoc_functions.py
statmanager/regression_functions.py
statmanager/reliability_functions.py
statmanager/selector_for_howtouse_eng.csv
statmanager/selector_for_howtouse_kor.csv
statmanager/setup.py
statmanager/statmanager.py
statmanager/ways_anova_functions.py
statmanager/within_group_functions.py
statmanager_kr-1.8.1.15.dist-info/LICENSE
statmanager_kr-1.8.1.15.dist-info/METADATA
statmanager_kr-1.8.1.15.dist-info/WHEEL
statmanager_kr-1.8.1.15.dist-info/top_level.txt
statmanager_kr-1.8.1.15.dist-info/RECORD
