Metadata-Version: 2.1
Name: statmanager-kr
Version: 1.8.1.15
Summary: Open-source statistical package in Python based on the Pandas
Home-page: https://cslee145.notion.site/60cbfcbc90614fe990e02ab8340630cc?v=4991650ae5ce4427a215d1043802f5c0&pvs=4
Download-URL: https://github.com/ckdckd145/statmanager-kr
Author: ckdckd145
Author-email: ckdckd145@gmail.com
License: MIT
Keywords: statistic,socialscience,stats,analysis,data,research,science
Classifier: License :: OSI Approved :: MIT License
Classifier: Intended Audience :: Science/Research
Classifier: Programming Language :: Python :: 3.10
Classifier: Programming Language :: Python :: 3.11
Classifier: Programming Language :: Python :: 3.12
Classifier: Operating System :: Microsoft :: Windows :: Windows 10
Classifier: Operating System :: Microsoft :: Windows :: Windows 11
Classifier: Operating System :: MacOS
Classifier: Operating System :: POSIX :: Linux
Classifier: Natural Language :: Korean
Classifier: Natural Language :: English
Classifier: Development Status :: 4 - Beta
Classifier: Topic :: Scientific/Engineering
Requires-Python: >=3.10
License-File: LICENSE
Requires-Dist: pandas
Requires-Dist: scipy
Requires-Dist: statsmodels
Requires-Dist: matplotlib
Requires-Dist: seaborn
Requires-Dist: XlsxWriter
